CHANGES.rst
CONTRIBUTORS.rst
MANIFEST.in
README.rst
setup.cfg
setup.py
docs/README
docs/_images/README
docs/source/conf.py
docs/source/configuration.rst
docs/source/index.rst
docs/source/_static/logo.png
docs/source/_templates/empty
src/ps/__init__.py
src/ps.diazo.realia.egg-info/PKG-INFO
src/ps.diazo.realia.egg-info/SOURCES.txt
src/ps.diazo.realia.egg-info/dependency_links.txt
src/ps.diazo.realia.egg-info/entry_points.txt
src/ps.diazo.realia.egg-info/namespace_packages.txt
src/ps.diazo.realia.egg-info/not-zip-safe
src/ps.diazo.realia.egg-info/requires.txt
src/ps.diazo.realia.egg-info/top_level.txt
src/ps/diazo/__init__.py
src/ps/diazo/realia/__init__.py
src/ps/diazo/realia/config.py
src/ps/diazo/realia/configure.zcml
src/ps/diazo/realia/interfaces.py
src/ps/diazo/realia/migration.py
src/ps/diazo/realia/profiles.zcml
src/ps/diazo/realia/setuphandlers.py
src/ps/diazo/realia/testing.py
src/ps/diazo/realia/Extensions/install.py
src/ps/diazo/realia/diazo_resources/favicon.ico
src/ps/diazo/realia/diazo_resources/index.html
src/ps/diazo/realia/diazo_resources/manifest.cfg
src/ps/diazo/realia/diazo_resources/preview.png
src/ps/diazo/realia/diazo_resources/rules.xml
src/ps/diazo/realia/diazo_resources/assets/css/realia-blue.css
src/ps/diazo/realia/diazo_resources/assets/css/realia-brown-dark.css
src/ps/diazo/realia/diazo_resources/assets/css/realia-brown.css
src/ps/diazo/realia/diazo_resources/assets/css/realia-gray-blue.css
src/ps/diazo/realia/diazo_resources/assets/css/realia-gray-brown-dark.css
src/ps/diazo/realia/diazo_resources/assets/css/realia-gray-brown.css
src/ps/diazo/realia/diazo_resources/assets/css/realia-gray-green-light.css
src/ps/diazo/realia/diazo_resources/assets/css/realia-gray-green.css
src/ps/diazo/realia/diazo_resources/assets/css/realia-gray-magenta.css
src/ps/diazo/realia/diazo_resources/assets/css/realia-gray-orange.css
src/ps/diazo/realia/diazo_resources/assets/css/realia-gray-red.css
src/ps/diazo/realia/diazo_resources/assets/css/realia-gray-turquiose.css
src/ps/diazo/realia/diazo_resources/assets/css/realia-gray-violet.css
src/ps/diazo/realia/diazo_resources/assets/css/realia-green-light.css
src/ps/diazo/realia/diazo_resources/assets/css/realia-green.css
src/ps/diazo/realia/diazo_resources/assets/css/realia-magenta.css
src/ps/diazo/realia/diazo_resources/assets/css/realia-orange.css
